mdxtconnect/__init__.py
mdxtconnect/_api.py
mdxtconnect/_config.py
mdxtconnect-1.1.0.dist-info/LICENSE
mdxtconnect-1.1.0.dist-info/METADATA
mdxtconnect-1.1.0.dist-info/WHEEL
mdxtconnect-1.1.0.dist-info/top_level.txt
mdxtconnect-1.1.0.dist-info/RECORD
