Metadata-Version: 2.1
Name: mdxtconnect
Version: 1.1.0
Summary: MDXT Connect / Data Marketplace access from Jupyter/IPython
Home-page: https://www.mdxtechnology.com
Author: MDX Technology
Author-email: support@mdxtechnology.com
License: UNKNOWN
Platform: UNKNOWN
Classifier: Programming Language :: Python :: 3
Classifier: License :: OSI Approved :: MIT License
Classifier: Operating System :: OS Independent
Requires-Python: >=3.6
License-File: LICENSE
Requires-Dist: requests (>=2.0.0)
Requires-Dist: pandas (>=0.23)
